parsehub/__init__.py
parsehub/client.py
parsehub/exceptions.py
parsehub/session.py
parsehub/utils.py
parsehub_client-0.0.6.dist-info/LICENSE
parsehub_client-0.0.6.dist-info/METADATA
parsehub_client-0.0.6.dist-info/WHEEL
parsehub_client-0.0.6.dist-info/top_level.txt
parsehub_client-0.0.6.dist-info/RECORD
