Metadata-Version: 2.1
Name: parsehub-client
Version: 0.0.6
Summary: ParseHub API client
Home-page: https://github.com/ebragas/parsehub-client
Author: Eric Bragas
Author-email: ericbragas412@gmail.com
License: MIT
Platform: UNKNOWN
Classifier: License :: OSI Approved :: MIT License
Classifier: Programming Language :: Python :: 3
Classifier: Programming Language :: Python :: 3.7
Requires-Dist: requests
